srunx/__init__.py
srunx/callbacks.py
srunx/client.py
srunx/config.py
srunx/exceptions.py
srunx/formatters.py
srunx/logging.py
srunx/models.py
srunx/py.typed
srunx/runner.py
srunx/utils.py
srunx/cli/__init__.py
srunx/cli/main.py
srunx/cli/monitor.py
srunx/cli/workflow.py
srunx/monitor/__init__.py
srunx/monitor/base.py
srunx/monitor/job_monitor.py
srunx/monitor/report_types.py
srunx/monitor/resource_monitor.py
srunx/monitor/scheduler.py
srunx/monitor/types.py
srunx/ssh/__init__.py
srunx/ssh/example.py
srunx/ssh/cli/__init__.py
srunx/ssh/cli/commands.py
srunx/ssh/cli/main.py
srunx/ssh/cli/profile.py
srunx/ssh/cli/profile_impl.py
srunx/ssh/cli/submit.py
srunx/ssh/cli/test.py
srunx/ssh/core/__init__.py
srunx/ssh/core/client.py
srunx/ssh/core/config.py
srunx/ssh/core/proxy_client.py
srunx/ssh/core/ssh_config.py
srunx/ssh/helpers/__init__.py
srunx/ssh/helpers/proxy_helper.py
srunx/templates/advanced.slurm.jinja
srunx/templates/base.slurm.jinja
srunx-0.8.0.dist-info/METADATA
srunx-0.8.0.dist-info/WHEEL
srunx-0.8.0.dist-info/entry_points.txt
srunx-0.8.0.dist-info/licenses/LICENCE
srunx-0.8.0.dist-info/RECORD
