Metadata-Version: 2.4
Name: srunx
Version: 0.8.0
Summary: Slurm job workflow management
Author-email: ksterx <kostonerx@gmail.com>
License-File: LICENCE
Requires-Python: >=3.12
Requires-Dist: apscheduler>=3.10.0
Requires-Dist: jinja2>=3.1.6
Requires-Dist: loguru>=0.7.3
Requires-Dist: paramiko>=4.0.0
Requires-Dist: pydantic>=2.11.5
Requires-Dist: pyyaml>=6.0.2
Requires-Dist: rich>=14.0.0
Requires-Dist: slack-sdk>=3.35.0
Requires-Dist: typer>=0.17.3
